{"_source":"SartajPHP Core","_language":"php","type":"php-class","name":"Pagination","namespace":"","fqcn":"Pagination","file":"components\/uikitdef\/\/bootstrap\/data\/Pagination.php","source_root":".\/vendor\/sartajphp\/sartajphp\/res","source_url":"https:\/\/www.sartajphp.com\/api\/Pagination.html","purpose":"","properties":[{"name":"pageNo","visibility":["public"],"doc":""},{"name":"totalPages","visibility":["public"],"doc":""},{"name":"totalRows","visibility":["public"],"doc":""},{"name":"perPageRows","visibility":["public"],"doc":""},{"name":"sql","visibility":["public"],"doc":""},{"name":"pageCountSQL","visibility":["public"],"doc":""},{"name":"result","visibility":["public"],"doc":""},{"name":"row","visibility":["public"],"doc":""},{"name":"linkno","visibility":["public"],"doc":""},{"name":"extraData","visibility":["public"],"doc":""},{"name":"strFormat","visibility":["public"],"doc":""},{"name":"fieldNames","visibility":["public"],"doc":""},{"name":"headNames","visibility":["public"],"doc":""},{"name":"colwidths","visibility":["public"],"doc":""},{"name":"where","visibility":["public"],"doc":""},{"name":"app","visibility":["public"],"doc":""},{"name":"blnEdit","visibility":["public"],"doc":""},{"name":"blnDelete","visibility":["public"],"doc":""},{"name":"eventName","visibility":["public"],"doc":""},{"name":"editeventName","visibility":["public"],"doc":""},{"name":"deleventName","visibility":["public"],"doc":""},{"name":"cacheTime","visibility":["public"],"doc":""},{"name":"buttonnext","visibility":["public"],"doc":""},{"name":"buttonprev","visibility":["public"],"doc":""},{"name":"page_links","visibility":["public"],"doc":""},{"name":"name","visibility":["protected"],"doc":"\/** @var string Name of Component *\/"},{"name":"tagName","visibility":["public"],"doc":"\/** @var string HTML Tag Name of Component *\/"},{"name":"value","visibility":["public"],"doc":"\/** @var string value of Component, depend on component code *\/"},{"name":"defvalue","visibility":["public"],"doc":"\/** @var string Default Value of Component *\/"},{"name":"dataType","visibility":["public"],"doc":"\/** @var string Data Type(STRING) of value of Component *\/"},{"name":"dtable","visibility":["public"],"doc":"\/** @var string Bind with Database Table *\/"},{"name":"dfield","visibility":["public"],"doc":"\/** @var string Bind with Database Table Field *\/"},{"name":"dataBound","visibility":["public"],"doc":"\/** @var boolean Database Bind Flag *\/"},{"name":"blnDontFill","visibility":["public"],"doc":"\/** @var boolean Database Fill Flag *\/"},{"name":"blnDontSubmit","visibility":["public"],"doc":"\/** @var boolean Form Submit Flag *\/"},{"name":"blnDontInsert","visibility":["public"],"doc":"\/** @var boolean Database Insert Flag *\/"},{"name":"blnDontUpdate","visibility":["public"],"doc":"\/** @var boolean Database Update Flag *\/"},{"name":"HTMLName","visibility":["public"],"doc":"\/** @var string HTML Tag Name *\/"},{"name":"HTMLID","visibility":["public"],"doc":"\/** @var string HTML Tag id *\/"},{"name":"visible","visibility":["public"],"doc":"\/** @var boolean Default true *\/"},{"name":"renderMe","visibility":["public"],"doc":"\/** @var boolean Default true *\/"},{"name":"renderTag","visibility":["public"],"doc":"\/** @var boolean Default true *\/"},{"name":"issubmit","visibility":["public"],"doc":"\/** @var boolean Submit flag check component submit by browser or not *\/"},{"name":"blnendtag","visibility":["public"],"doc":"\/** @var boolean Set HTML Closing Tag *\/"},{"name":"mypath","visibility":["public"],"doc":"\/** @var string Component File Directory *\/"},{"name":"myrespath","visibility":["public"],"doc":"\/** @var string Component File Directory As URL *\/"},{"name":"cfilename","visibility":["public"],"doc":""},{"name":"cfilepath","visibility":["public"],"doc":""},{"name":"element","visibility":["public"],"doc":"\/** @var \\Sphp\\tools\\NodeTag Component Node Tag *\/"},{"name":"parentobj","visibility":["public"],"doc":"\/** @var \\Sphp\\tools\\Component Component Object *\/"},{"name":"frontobj","visibility":["protected"],"doc":"\/** @var \\Sphp\\tools\\FrontFile Parent FrontFile *\/"},{"name":"children","visibility":["protected"],"doc":""},{"name":"proplist","visibility":["protected"],"doc":""},{"name":"styler","visibility":["protected"],"doc":"\/** @var int  *\/"}],"methods":[{"name":"onit","visibility":["protected"],"params":[],"doc":""},{"name":"genhelpPropList","visibility":["protected"],"params":[],"doc":""},{"name":"getEventURL","visibility":["public"],"params":["eventName","evtp","Appgate","extra","newBasePath","blnSesID"],"doc":""},{"name":"getRow","visibility":["public"],"params":["field"],"doc":""},{"name":"fu_setMsgName","visibility":["public"],"params":["val"],"doc":""},{"name":"fu_setPrimaryKey","visibility":["public"],"params":["val"],"doc":""},{"name":"fu_setSQL","visibility":["public"],"params":["sql"],"doc":""},{"name":"fu_setPageCountSQL","visibility":["public"],"params":["sql"],"doc":""},{"name":"fu_setPerPageRows","visibility":["public"],"params":["val"],"doc":""},{"name":"fu_setExtraData","visibility":["public"],"params":["val"],"doc":""},{"name":"setPageNo","visibility":["public"],"params":["val"],"doc":""},{"name":"getPageNo","visibility":["public"],"params":[],"doc":""},{"name":"setLinkNo","visibility":["public"],"params":["val"],"doc":""},{"name":"fu_setCacheFile","visibility":["public"],"params":["val"],"doc":""},{"name":"fu_setCacheSave","visibility":["public"],"params":[],"doc":""},{"name":"fu_setCacheKey","visibility":["public"],"params":["val"],"doc":""},{"name":"fu_setCacheTime","visibility":["public"],"params":["val"],"doc":""},{"name":"fu_setFieldNames","visibility":["public"],"params":["val"],"doc":""},{"name":"fu_setHeaderNames","visibility":["public"],"params":["val"],"doc":""},{"name":"fu_setColWidths","visibility":["public"],"params":["val"],"doc":""},{"name":"fu_setWhere","visibility":["public"],"params":["val"],"doc":""},{"name":"fu_setApp","visibility":["public"],"params":["val"],"doc":""},{"name":"fu_setAjax","visibility":["public"],"params":[],"doc":""},{"name":"fu_setEdit","visibility":["public"],"params":[],"doc":""},{"name":"fu_setDelete","visibility":["public"],"params":[],"doc":""},{"name":"getPageBar","visibility":["public"],"params":[],"doc":""},{"name":"getButtonNext","visibility":["public"],"params":[],"doc":""},{"name":"getButtonPrev","visibility":["public"],"params":[],"doc":""},{"name":"fu_setHeader","visibility":["public"],"params":["val"],"doc":""},{"name":"fu_setFooter","visibility":["public"],"params":["val"],"doc":""},{"name":"fu_unsetDialog","visibility":["public"],"params":[],"doc":""},{"name":"fu_unsetAddButton","visibility":["public"],"params":[],"doc":""},{"name":"executeSQL","visibility":["public"],"params":[],"doc":""},{"name":"oncreate","visibility":["protected"],"params":["element"],"doc":""},{"name":"startAJAX","visibility":["public"],"params":[],"doc":""},{"name":"onjsrender","visibility":["protected"],"params":[],"doc":""},{"name":"onprerender","visibility":["protected"],"params":[],"doc":""},{"name":"onholder","visibility":["protected"],"params":["obj"],"doc":""}]}