{"_source":"SartajPHP Core","_language":"php","type":"php-class","name":"SessionClass","namespace":"Sphp\\tools","fqcn":"Sphp\\tools\\SessionClass","file":"Score\/SphpDoc\/extd\/SessionClass.php","source_root":".\/vendor\/sartajphp\/sartajphp\/res","source_url":"https:\/\/www.sartajphp.com\/api\/Sphp.tools.SessionClass.html","purpose":"\/**\r\n * Description of SessionClass\r\n *\r\n * @author Sartaj Singh\r\n *\/","properties":[],"methods":[{"name":"onstart","visibility":["public"],"params":[],"doc":""},{"name":"onend","visibility":["public"],"params":[],"doc":""}]}